{"title":"测试","slug":"测试","date":"2021-02-12","updated":"2021-02-12","comments":true,"path":"api/posts/37773.json","excerpt":null,"cover":"../images/QQ%E5%9B%BE%E7%89%8720201201132631.jpg","covers":["../images/QQ%E5%9B%BE%E7%89%8720201201132631.jpg"],"content":"<p><img src=\"../images/QQ%E5%9B%BE%E7%89%8720201201132631.jpg\" alt=\"QQ 图片 20201201132631\"></p>\n","url":"/posts/37773/","min2read":"1","word4post":0,"prev_post":null,"next_post":{"title":"黑苹果 win 双系统安装","url":"/posts/43789/"},"toc":"","categories":[],"tags":[]}